quick_pdf/__init__.py
quick_pdf/merge.py
quick_pdf-0.1.1.dist-info/entry_points.txt
quick_pdf-0.1.1.dist-info/WHEEL
quick_pdf-0.1.1.dist-info/METADATA
quick_pdf-0.1.1.dist-info/RECORD
